cdsr_pack/__init__.py
cdsr_pack/builder.py
cdsr_pack/decoder.py
cdsr_pack-0.0.2.dist-info/LICENSE
cdsr_pack-0.0.2.dist-info/METADATA
cdsr_pack-0.0.2.dist-info/WHEEL
cdsr_pack-0.0.2.dist-info/top_level.txt
cdsr_pack-0.0.2.dist-info/RECORD
