Metadata-Version: 2.1
Name: cdsr-pack
Version: 0.0.2
Summary: CDSR pack is a package to store common functions from CDSR project.
Home-page: https://github.com/inpe-cdsr/cdsr_pack
Author: INPE
Author-email: atus@inpe.br
License: UNKNOWN
Project-URL: Bug Tracker, https://github.com/inpe-cdsr/cdsr_pack/issues
Platform: UNKNOWN
Classifier: Programming Language :: Python :: 3
Classifier: License :: OSI Approved :: MIT License
Classifier: Operating System :: OS Independent
Requires-Python: >=3.6
License-File: LICENSE
